gooddata_afm_client/__init__.py
gooddata_afm_client/api_client.py
gooddata_afm_client/configuration.py
gooddata_afm_client/exceptions.py
gooddata_afm_client/model_utils.py
gooddata_afm_client/rest.py
gooddata_afm_client/api/__init__.py
gooddata_afm_client/api/actions_api.py
gooddata_afm_client/api/computation_api.py
gooddata_afm_client/apis/__init__.py
gooddata_afm_client/model/__init__.py
gooddata_afm_client/model/absolute_date_filter.py
gooddata_afm_client/model/absolute_date_filter_absolute_date_filter.py
gooddata_afm_client/model/abstract_measure_value_filter.py
gooddata_afm_client/model/afm.py
gooddata_afm_client/model/afm_execution.py
gooddata_afm_client/model/afm_execution_response.py
gooddata_afm_client/model/afm_identifier.py
gooddata_afm_client/model/afm_local_identifier.py
gooddata_afm_client/model/afm_object_identifier.py
gooddata_afm_client/model/afm_object_identifier_attribute.py
gooddata_afm_client/model/afm_object_identifier_attribute_identifier.py
gooddata_afm_client/model/afm_object_identifier_core.py
gooddata_afm_client/model/afm_object_identifier_core_identifier.py
gooddata_afm_client/model/afm_object_identifier_dataset.py
gooddata_afm_client/model/afm_object_identifier_dataset_identifier.py
gooddata_afm_client/model/afm_object_identifier_identifier.py
gooddata_afm_client/model/afm_object_identifier_label.py
gooddata_afm_client/model/afm_object_identifier_label_identifier.py
gooddata_afm_client/model/afm_valid_objects_query.py
gooddata_afm_client/model/afm_valid_objects_response.py
gooddata_afm_client/model/arithmetic_measure_definition.py
gooddata_afm_client/model/arithmetic_measure_definition_arithmetic_measure.py
gooddata_afm_client/model/attribute_execution_result_header.py
gooddata_afm_client/model/attribute_filter.py
gooddata_afm_client/model/attribute_filter_elements.py
gooddata_afm_client/model/attribute_format.py
gooddata_afm_client/model/attribute_header_out.py
gooddata_afm_client/model/attribute_header_out_attribute_header.py
gooddata_afm_client-1.3.0.dist-info/LICENSE.txt
gooddata_afm_client-1.3.0.dist-info/METADATA
gooddata_afm_client-1.3.0.dist-info/WHEEL
gooddata_afm_client-1.3.0.dist-info/top_level.txt
gooddata_afm_client-1.3.0.dist-info/RECORD
